[
    {
      "_id": "6331aa19f87d4ba40280cb1c",
      "image": "images/Review.png",
      "name": "Flora Serrano",
      "review": "The cycle I purchase was very well maintained and comfortable"
    },
    {
      "_id": "6331aa19a6a0f231d7c6255f",
      "image": "images/Review.png",
      "name": "Ratliff Cobb",
      "review": "This is a Great cycle bro ... Outstanding Performance"
    },
    {
      "_id": "6331aa19fea8dc90c6d362da",
      "image": "images/Review.png",
      "name": "Bernard Murray",
      "review": "The cycle is Awesome"
    },
    {
      "_id": "6331aa19294db89cad5729c9",
      "image": "images/Review.png",
      "name": "Autumn Graves",
      "review": "This is a super bike like that..I highly recommended the cycle is best."
    },
    {
      "_id": "6331aa193341e70e05d2f692",
      "image": "images/Review.png",
      "name": "Franklin Higgins",
      "review": "WOW!! This is a great cycle."
    },
    {
      "_id": "6331aa19d5ee8cc6630563aa",
      "image": "images/Review.png",
      "name": "Pope Griffin",
      "review": "Speechless!! The cycle is super.."
    }
  ]